[
  {
    "type": "heading",
    "zh": "約拿的禱告"
  },
  {
    "verse": 1,
    "zh": "約拿在魚腹中禱告耶和華－他的神，",
    "ko": "요나가 물고기 뱃속에서 그 하나님 여호와께 기도하여"
  },
  {
    "verse": 2,
    "zh": "說： 我遭遇患難求告耶和華， 你就應允我； 從陰間的深處呼求， 你就俯聽我的聲音。",
    "ko": "가로되 내가 받는 고난을 인하여 여호와께 불러 아뢰었삽더니 주께서 내게 대답하셨고 내가 스올의 뱃속에서 부르짖었삽더니 주께서 나의 음성을 들으셨나이다"
  },
  {
    "verse": 3,
    "zh": "你將我投下深淵， 就是海的深處； 大水環繞我， 你的波浪洪濤都漫過我身。",
    "ko": "주께서 나를 깊음 속 바다 가운데 던지셨으므로 큰 물이 나를 둘렀고 주의 파도와 큰 물결이 다 내 위에 넘쳤나이다"
  },
  {
    "verse": 4,
    "zh": "我說：我從你眼前雖被驅逐， 我仍要仰望你的聖殿。",
    "ko": "내가 말하기를 내가 주의 목전에서 쫓겨났을지라도 다시 주의 성전을 바라보겠다 하였나이다"
  },
  {
    "verse": 5,
    "zh": "諸水環繞我，幾乎淹沒我； 深淵圍住我； 海草纏繞我的頭。",
    "ko": "물이 나를 둘렀으되 영혼까지 하였사오며 깊음이 나를 에웠고 바다 풀이 내 머리를 쌌나이다"
  },
  {
    "verse": 6,
    "zh": "我下到山根， 地的門將我永遠關住。 耶和華－我的神啊， 你卻將我的性命從坑中救出來。",
    "ko": "내가 산의 뿌리까지 내려갔사오며 땅이 그 빗장으로 나를 오래도록 막았사오나 나의 하나님 여호와여 주께서 내 생명을 구덩이에서 건지셨나이다"
  },
  {
    "verse": 7,
    "zh": "我心在我裏面發昏的時候， 我就想念耶和華。 我的禱告進入你的聖殿， 達到你的面前。",
    "ko": "내 영혼이 내 속에서 피곤할 때에 내가 여호와를 생각하였삽더니 내 기도가 주께 이르렀사오며 주의 성전에 미쳤나이다"
  },
  {
    "verse": 8,
    "zh": "那信奉虛無之神的人， 離棄憐愛他們的主；",
    "ko": "무릇 거짓되고 헛된 것을 숭상하는 자는 자기에게 베푸신 은혜를 버렸사오나"
  },
  {
    "verse": 9,
    "zh": "但我必用感謝的聲音獻祭與你。 我所許的願，我必償還。 救恩出於耶和華。",
    "ko": "나는 감사하는 목소리로 주께 제사를 드리며 나의 서원을 주께 갚겠나이다 구원은 여호와께로서 말미암나이다 하니라"
  },
  {
    "verse": 10,
    "zh": "耶和華吩咐魚，魚就把約拿吐在旱地上。",
    "ko": "여호와께서 물고기에게 명하시매 요나를 육지에 토하니라"
  }
]
