[
  {
    "type": "heading",
    "zh": "以薩迦的後裔"
  },
  {
    "verse": 1,
    "zh": "以薩迦的兒子是陀拉、普瓦、雅述、伸崙，共四人。",
    "ko": "잇사갈의 아들들은 돌라와 부아와 야숩과 시므론 네 사람이며"
  },
  {
    "verse": 2,
    "zh": "陀拉的兒子是烏西、利法雅、耶勒、雅買、易伯散、示母利，都是陀拉的族長，是大能的勇士。到大衛年間，他們的人數共有二萬二千六百名。",
    "ko": "돌라의 아들들은 웃시와 르바야와 여리엘과 야매와 입삼과 스므엘이니 다 그 아비 돌라의 집 족장이라 대대로 용사더니 다윗 때에 이르러는 그 수효가 이만 이천육백 명이었더라"
  },
  {
    "verse": 3,
    "zh": "烏西的兒子是伊斯拉希；伊斯拉希的兒子是米迦勒、俄巴底亞、約珥、伊示雅，共五人，都是族長。",
    "ko": "웃시의 아들은 이스라히야요 이스라히야의 아들들은 미가엘과 오바댜와 요엘과 잇시야 다섯 사람이 모두 족장이며"
  },
  {
    "verse": 4,
    "zh": "他們所率領的，按著宗族出戰的軍隊，共有三萬六千人，因為他們的妻和子眾多。",
    "ko": "저희와 함께한 자는 그 보계와 종족대로 능히 출전할만한 군대가 삼만 육천 인이니 이는 그 처자가 많은 연고며"
  },
  {
    "verse": 5,
    "zh": "他們的族弟兄在以薩迦各族中都是大能的勇士，按著家譜計算共有八萬七千人。",
    "ko": "그 형제 잇사갈의 모든 종족은 다 큰 용사라 그 보계대로 계수하면 팔만 칠천 인이었더라"
  },
  {
    "type": "heading",
    "zh": "便雅憫和但的後裔"
  },
  {
    "verse": 6,
    "zh": "便雅憫的兒子是比拉、比結、耶疊，共三人。",
    "ko": "베냐민의 아들들은 벨라와 베겔과 여디아엘 세 사람이며"
  },
  {
    "verse": 7,
    "zh": "比拉的兒子是以斯本、烏西、烏薛、耶利摩、以利，共五人，都是族長，是大能的勇士。按著家譜計算，他們的子孫共有二萬二千零三十四人。",
    "ko": "벨라의 아들들은 에스본과 우시와 웃시엘과 여리못과 이리 다섯 사람이니 다 그 집의 족장이요 큰 용사라 그 보계대로 계수하면 이만 이천삼십사 인이며"
  },
  {
    "verse": 8,
    "zh": "比結的兒子是細米拉、約阿施、以利以謝、以利約乃、暗利、耶利摩、亞比雅、亞拿突、亞拉篾。這都是比結的兒子。",
    "ko": "베겔의 아들들은 스미라와 요아스와 엘리에셀과 엘료에내와 오므리와 여레못과 아비야와 아나돗과 알레멧이니 베겔의 아들들은 이러하며"
  },
  {
    "verse": 9,
    "zh": "他們都是族長，是大能的勇士。按著家譜計算，他們的子孫共有二萬零二百人。",
    "ko": "저희는 다 그 집의 족장이요 큰 용사라 그 자손을 보계대로 계수하면 이만 이백 인이며"
  },
  {
    "verse": 10,
    "zh": "耶疊的兒子是比勒罕；比勒罕的兒子是耶烏施、便雅憫、以忽、基拿拿、細坦、他施、亞希沙哈。",
    "ko": "여디아엘의 아들은 빌한이요 빌한의 아들들은 여우스와 베냐민과 에훗과 그나아나와 세단과 다시스와 아히사할이니"
  },
  {
    "verse": 11,
    "zh": "這都是耶疊的兒子，都是族長，是大能的勇士；他們的子孫能上陣打仗的，共有一萬七千二百人。",
    "ko": "이 여디아엘의 아들들은 그 집의 족장이요 큰 용사라 그 자손 중에 능히 출전할만한 자가 일만 칠천이백 인이며"
  },
  {
    "verse": 12,
    "zh": "還有以珥的兒子書品、戶品，並亞黑的兒子戶伸。",
    "ko": "일의 아들은 숩빔과 훕빔이요 아헬의 아들은 후심이더라"
  },
  {
    "type": "heading",
    "zh": "拿弗他利的後裔"
  },
  {
    "verse": 13,
    "zh": "拿弗他利的兒子是雅薛、沽尼、耶色、沙龍。這都是辟拉的子孫。",
    "ko": "납달리의 아들들은 야시엘과 구니와 예셀과 살룸이니 이는 빌하의 손자더라"
  },
  {
    "type": "heading",
    "zh": "瑪拿西的後裔"
  },
  {
    "verse": 14,
    "zh": "瑪拿西的兒子亞斯列是他妾亞蘭人所生的，又生了基列之父瑪吉。",
    "ko": "므낫세의 아들들 그 처의 소생은 아스리엘이요 그 첩 아람 여인의 소생은 길르앗의 아비 마길이니"
  },
  {
    "verse": 15,
    "zh": "瑪吉娶的妻是戶品、書品的妹子，名叫瑪迦。瑪拿西的次子名叫西羅非哈；西羅非哈但有幾個女兒。",
    "ko": "마길은 훕빔과 숩빔의 누이 마아가라 하는 이에게 장가들었더라 므낫세의 둘째 아들의 이름은 슬로브핫이니 슬로브핫은 딸들만 낳았으며"
  },
  {
    "verse": 16,
    "zh": "瑪吉的妻瑪迦生了一個兒子，起名叫毗利施。毗利施的兄弟名叫示利施；示利施的兒子是烏蘭和利金。",
    "ko": "마길의 아내 마아가는 아들을 낳아 그 이름을 베레스라 하였으며 그 아우는 이름이 세레스며 세레스의 아들은 울람과 라겜이요"
  },
  {
    "verse": 17,
    "zh": "烏蘭的兒子是比但。這都是基列的子孫。基列是瑪吉的兒子，瑪吉是瑪拿西的兒子。",
    "ko": "울람의 아들은 브단이니 이는 다 길르앗의 자손이라 길르앗은 마길의 아들이요 므낫세의 손자며"
  },
  {
    "verse": 18,
    "zh": "基列的妹子哈摩利吉生了伊施荷、亞比以謝、瑪拉。（",
    "ko": "그 누이 함몰레겟은 이스훗과 아비에셀과 말라를 낳았고"
  },
  {
    "verse": 19,
    "zh": "示米大的兒子是亞現、示劍、利克希、阿尼安。）",
    "ko": "스미다의 아들은 아히안과 세겜과 릭히와 아니암이더라"
  },
  {
    "type": "heading",
    "zh": "以法蓮的後裔"
  },
  {
    "verse": 20,
    "zh": "以法蓮的兒子是書提拉；書提拉的兒子是比列；比列的兒子是他哈；他哈的兒子是以拉大；以拉大的兒子是他哈；",
    "ko": "에브라임의 아들은 수델라요 그 아들은 베렛이요 그 아들은 다핫이요 그 아들은 엘르아다요 그 아들은 다핫이요"
  },
  {
    "verse": 21,
    "zh": "他哈的兒子是撒拔；撒拔的兒子是書提拉。以法蓮又生以謝、以列；這二人因為下去奪取迦特人的牲畜，被本地的迦特人殺了。",
    "ko": "그 아들은 사밧이요 그 아들은 수델라며 저가 또 에셀과 엘르앗을 낳았더니 저희가 가드 토인에게 죽임을 당하였으니 이는 저희가 내려가서 가드 사람의 짐승을 빼앗고자 하였음이라"
  },
  {
    "verse": 22,
    "zh": "他們的父親以法蓮為他們悲哀了多日，他的弟兄都來安慰他。",
    "ko": "그 아비 에브라임이 위하여 여러 날 슬퍼하므로 그 형제가 와서 위로하였더라"
  },
  {
    "verse": 23,
    "zh": "以法蓮與妻同房，他妻就懷孕生了一子，以法蓮因為家裏遭禍，就給這兒子起名叫比利亞。",
    "ko": "그 후에 에브라임이 그 아내와 동침하였더니 아내가 잉태하여 아들을 낳으니 그 집이 재앙을 받았으므로 그 이름을 브리아라 하였더라"
  },
  {
    "verse": 24,
    "zh": "他的女兒名叫舍伊拉，就是建築上伯‧和崙、下伯‧和崙與烏羨‧舍伊拉的。",
    "ko": "에브라임의 딸은 세에라니 저가 아래 윗 벧호론과 우센세에라를 세웠더라"
  },
  {
    "verse": 25,
    "zh": "比利亞的兒子是利法和利悉。利悉的兒子是他拉；他拉的兒子是他罕；",
    "ko": "브리아의 아들들은 레바와 레셉이요 레셉의 아들은 델라요 그 아들은 다한이요"
  },
  {
    "verse": 26,
    "zh": "他罕的兒子是拉但；拉但的兒子是亞米忽；亞米忽的兒子是以利沙瑪；",
    "ko": "그 아들은 라단이요 그 아들은 암미훗이요 그 아들은 엘리사마요"
  },
  {
    "verse": 27,
    "zh": "以利沙瑪的兒子是嫩；嫩的兒子是約書亞。",
    "ko": "그 아들은 눈이요 그 아들은 여호수아더라"
  },
  {
    "verse": 28,
    "zh": "以法蓮人的地業和住處是伯特利與其村莊；東邊拿蘭，西邊基色與其村莊；示劍與其村莊，直到迦薩與其村莊；",
    "ko": "에브라임 자손의 산업과 거처는 벧엘과 그 향리요 동에는 나아란이요 서에는 게셀과 그 향리며 또 세겜과 그 향리니 아사와 그 향리까지며"
  },
  {
    "verse": 29,
    "zh": "還有靠近瑪拿西人的境界，伯‧善與其村莊；他納與其村莊；米吉多與其村莊；多珥與其村莊。以色列兒子約瑟的子孫住在這些地方。",
    "ko": "또 므낫세 자손의 지경에 가까운 벧스안과 그 향리와 다아낙과 그 향리와 므깃도와 그 향리와 돌과 그 향리라 이스라엘의 아들 요셉의 자손이 이 여러 곳에 거하였더라"
  },
  {
    "type": "heading",
    "zh": "亞設的後裔"
  },
  {
    "verse": 30,
    "zh": "亞設的兒子是音拿、亦施瓦、亦施韋、比利亞，還有他們的妹子西拉。",
    "ko": "아셀의 아들들은 임나와 이스와와 이스위와 브리아요 저희의 매제는 세라며"
  },
  {
    "verse": 31,
    "zh": "比利亞的兒子是希別、瑪結；瑪結是比撒威的父親。",
    "ko": "브리아의 아들들은 헤벨과 말기엘이니 말기엘은 비르사잇의 아비며"
  },
  {
    "verse": 32,
    "zh": "希別生雅弗勒、朔默、何坦，和他們的妹子書雅。",
    "ko": "헤벨은 야블렛과 소멜과 호담과 저희의 매제 수아를 낳았으며"
  },
  {
    "verse": 33,
    "zh": "雅弗勒的兒子是巴薩、賓哈、亞施法。這都是雅弗勒的兒子。",
    "ko": "야블렛의 아들들은 바삭과 빔할과 아스왓이니 야블렛의 아들은 이러하며"
  },
  {
    "verse": 34,
    "zh": "朔默的兒子是亞希、羅迦、耶戶巴、亞蘭。",
    "ko": "소멜의 아들들은 아히와 로가와 호바와 아람이요"
  },
  {
    "verse": 35,
    "zh": "朔默兄弟希連的兒子是瑣法、音那、示利斯、亞抹。",
    "ko": "그 아우 헬렘의 아들들은 소바와 임나와 셀레스와 아말이요"
  },
  {
    "verse": 36,
    "zh": "瑣法的兒子是書亞、哈尼弗、書阿勒、比利、音拉、",
    "ko": "소바의 아들들은 수아와 하르네벨과 수알과 베리와 이므라와"
  },
  {
    "verse": 37,
    "zh": "比悉、河得、珊瑪、施沙、益蘭、比拉。",
    "ko": "베셀과 훗과 사마와 실사와 이드란과 브에라요"
  },
  {
    "verse": 38,
    "zh": "益帖的兒子是耶孚尼、毗斯巴、亞拉。",
    "ko": "예델의 아들들은 여분네와 비스바와 아라요"
  },
  {
    "verse": 39,
    "zh": "烏拉的兒子是亞拉、漢尼業、利寫。",
    "ko": "울라의 아들들은 아라와 한니엘과 리시아니"
  },
  {
    "verse": 40,
    "zh": "這都是亞設的子孫，都是族長，是精壯大能的勇士，也是首領中的頭目，按著家譜計算，他們的子孫能出戰的共有二萬六千人。",
    "ko": "이는 다 아셀의 자손으로 족장이요 뽑힌 큰 용사요 방백의 두목이라 출전할만한 자를 그 보계대로 계수하면 이만 육천 인이었더라"
  }
]
