[
  {
    "type": "heading",
    "zh": "葡萄園之歌"
  },
  {
    "verse": 1,
    "zh": "我要為我所親愛的唱歌， 是我所愛者的歌，論他葡萄園的事： 我所親愛的有葡萄園在肥美的山岡上。",
    "ko": "내가 나의 사랑하는 자를 위하여 노래하되 나의 사랑하는 자의 포도원을 노래하리라 나의 사랑하는 자에게 포도원이 있음이여 심히 기름진 산에로다"
  },
  {
    "verse": 2,
    "zh": "他刨挖園子，撿去石頭， 栽種上等的葡萄樹， 在園中蓋了一座樓， 又鑿出壓酒池； 指望結好葡萄， 反倒結了野葡萄。",
    "ko": "땅을 파서 돌을 제하고 극상품 포도나무를 심었었도다 그 중에 망대를 세웠고 그 안에 술틀을 팠었도다 좋은 포도 맺기를 바랐더니 들 포도를 맺혔도다"
  },
  {
    "verse": 3,
    "zh": "耶路撒冷的居民和猶大人哪， 請你們現今在我與我的葡萄園中，斷定是非。",
    "ko": "예루살렘 거민과 유다 사람들아 구하노니 이제 나와 내 포도원 사이에 판단하라"
  },
  {
    "verse": 4,
    "zh": "我為我葡萄園所做之外， 還有甚麼可做的呢？ 我指望結好葡萄， 怎麼倒結了野葡萄呢？",
    "ko": "내가 내 포도원을 위하여 행한 것 외에 무엇을 더할 것이 있었으랴 내가 좋은 포도 맺기를 기다렸거늘 들 포도를 맺힘은 어찜인고"
  },
  {
    "verse": 5,
    "zh": "現在我告訴你們， 我要向我葡萄園怎樣行： 我必撤去籬笆，使它被吞滅， 拆毀牆垣，使它被踐踏。",
    "ko": "이제 내가 내 포도원에 어떻게 행할 것을 너희에게 이르리라 내가 그 울타리를 걷어 먹힘을 당케 하며 그 담을 헐어 짓밟히게 할 것이요"
  },
  {
    "verse": 6,
    "zh": "我必使它荒廢，不再修理， 不再鋤刨，荊棘蒺藜倒要生長。 我也必命雲不降雨在其上。",
    "ko": "내가 그것으로 황무케 하리니 다시는 가지를 자름이나 북을 돋우지 못하여 질려와 형극이 날 것이며 내가 또 구름을 명하여 그 위에 비를 내리지 말라 하리라 하셨으니"
  },
  {
    "verse": 7,
    "zh": "萬軍之耶和華的葡萄園就是以色列家； 他所喜愛的樹就是猶大人。 他指望的是公平， 誰知倒有暴虐； 指望的是公義， 誰知倒有冤聲。",
    "ko": "대저 만군의 여호와의 포도원은 이스라엘 족속이요 그의 기뻐하시는 나무는 유다 사람이라 그들에게 공평을 바라셨더니 도리어 포학이요 그들에게 의로움을 바라셨더니 도리어 부르짖음이었도다"
  },
  {
    "type": "heading",
    "zh": "人的惡行"
  },
  {
    "verse": 8,
    "zh": "禍哉！那些以房接房， 以地連地， 以致不留餘地的， 只顧自己獨居境內。",
    "ko": "가옥에 가옥을 연하며 전토에 전토를 더하여 빈 틈이 없도록 하고 이 땅 가운데서 홀로 거하려 하는 그들은 화 있을진저"
  },
  {
    "verse": 9,
    "zh": "我耳聞萬軍之耶和華說： 必有許多又大又美的房屋 成為荒涼，無人居住。",
    "ko": "만군의 여호와께서 내 귀에 말씀하시되 정녕히 허다한 가옥이 황폐하리니 크고 아름다울지라도 거할 자가 없을 것이며"
  },
  {
    "verse": 10,
    "zh": "三十畝葡萄園只出一罷特酒； 一賀梅珥穀種只結一伊法糧食。",
    "ko": "열흘갈이 포도원에 겨우 포도주 한 바트가 나겠고 한 호멜지기에는 간신히 한 에바가 나리라 하시도다"
  },
  {
    "verse": 11,
    "zh": "禍哉！那些清早起來追求濃酒， 留連到夜深，甚至因酒發燒的人。",
    "ko": "아침에 일찍이 일어나 독주를 따라가며 밤이 깊도록 머물러 포도주에 취하는 그들은 화 있을진저"
  },
  {
    "verse": 12,
    "zh": "他們在筵席上 彈琴，鼓瑟，擊鼓，吹笛，飲酒， 卻不顧念耶和華的作為， 也不留心他手所做的。",
    "ko": "그들이 연회에는 수금과 비파와 소고와 저와 포도주를 갖추었어도 여호와의 행하심을 관심치 아니하며 그의 손으로 하신 일을 생각지 아니하는도다"
  },
  {
    "verse": 13,
    "zh": "所以，我的百姓因無知就被擄去； 他們的尊貴人甚是飢餓， 群眾極其乾渴。",
    "ko": "이러므로 나의 백성이 무지함을 인하여 사로잡힐 것이요 그 귀한 자는 주릴 것이요 무리는 목마를 것이며"
  },
  {
    "verse": 14,
    "zh": "故此，陰間擴張其欲， 開了無限量的口； 他們的榮耀、群眾、繁華， 並快樂的人都落在其中。",
    "ko": "음부가 그 욕망을 크게 내어 한량 없이 그 입을 벌린즉 그들의 호화로움과 그들의 많은 무리와 그들의 떠드는 것과 그 중에서 연락하는 자가 거기 빠질 것이라"
  },
  {
    "verse": 15,
    "zh": "卑賤人被壓服； 尊貴人降為卑； 眼目高傲的人也降為卑。",
    "ko": "천한 자는 굴복되고 귀한 자는 낮아지고 오만한 자의 눈도 낮아질 것이로되"
  },
  {
    "verse": 16,
    "zh": "惟有萬軍之耶和華因公平而崇高； 聖者神因公義顯為聖。",
    "ko": "오직 만군의 여호와는 공평하므로 높임을 받으시며 거룩하신 하나님은 의로우시므로 거룩하다 함을 받으시리니"
  },
  {
    "verse": 17,
    "zh": "那時，羊羔必來吃草，如同在自己的草場； 豐肥人的荒場被遊行的人吃盡。",
    "ko": "그 때에는 어린 양들이 자기 초장에 있는 것 같이 먹을 것이요 살찐 자의 황무한 밭의 소산은 유리하는 자들이 먹으리라"
  },
  {
    "verse": 18,
    "zh": "禍哉！那些以虛假之細繩牽罪孽的人！ 他們又像以套繩拉罪惡，",
    "ko": "거짓으로 끈을 삼아 죄악을 끌며 수레 줄로 함 같이 죄악을 끄는 자는 화 있을진저"
  },
  {
    "verse": 19,
    "zh": "說：任他急速行，趕快成就他的作為， 使我們看看； 任以色列聖者所謀劃的臨近成就， 使我們知道。",
    "ko": "그들이 이르기를 그는 그 일을 속속히 이루어 우리로 보게 할 것이며 이스라엘의 거룩한 자는 그 도모를 속히 임하게 하여 우리로 알게 할 것이라 하는도다"
  },
  {
    "verse": 20,
    "zh": "禍哉！那些稱惡為善，稱善為惡， 以暗為光，以光為暗， 以苦為甜，以甜為苦的人。",
    "ko": "악을 선하다 하며 선을 악하다 하며 흑암으로 광명을 삼으며 광명으로 흑암을 삼으며 쓴 것으로 단 것을 삼으며 단 것으로 쓴 것을 삼는 그들은 화 있을진저"
  },
  {
    "verse": 21,
    "zh": "禍哉！那些自以為有智慧， 自看為通達的人。",
    "ko": "스스로 지혜롭다 하며 스스로 명철하다 하는 그들은 화 있을진저"
  },
  {
    "verse": 22,
    "zh": "禍哉！那些勇於飲酒， 以能力調濃酒的人。",
    "ko": "포도주를 마시기에 용감하며 독주를 빚기에 유력한 그들은 화 있을진저"
  },
  {
    "verse": 23,
    "zh": "他們因受賄賂，就稱惡人為義， 將義人的義奪去。",
    "ko": "그들은 뇌물로 인하여 악인을 의롭다 하고 의인에게서 그 의를 빼았는도다"
  },
  {
    "verse": 24,
    "zh": "火苗怎樣吞滅碎稭， 乾草怎樣落在火焰之中， 照樣，他們的根必像朽物， 他們的花必像灰塵飛騰； 因為他們厭棄萬軍之耶和華的訓誨， 藐視以色列聖者的言語。",
    "ko": "이로 인하여 불꽃이 그루터기를 삼킴 같이, 마른 풀이 불 속에 떨어짐 같이 그들의 뿌리가 썩겠고 꽃이 티끌처럼 날리리니 그들이 만군의 여호와의 율법을 버리며 이스라엘의 거룩하신 자의 말씀을 멸시하였음이라"
  },
  {
    "verse": 25,
    "zh": "所以，耶和華的怒氣向他的百姓發作。 他的手伸出攻擊他們，山嶺就震動； 他們的屍首在街市上好像糞土。 雖然如此，他的怒氣還未轉消； 他的手仍伸不縮。",
    "ko": "그러므로 여호와께서 자기 백성에게 노를 발하시고 손을 들어 그들을 치신지라 산들은 진동하며 그들의 시체는 거리 가운데 분토 같이 되었으나 그 노가 돌아서지 아니하였고 그 손이 오히려 펴졌느니라"
  },
  {
    "verse": 26,
    "zh": "他必豎立大旗，招遠方的國民， 發嘶聲叫他們從地極而來； 看哪，他們必急速奔來。",
    "ko": "기를 세우시고 먼 나라들을 불러 땅 끝에서부터 오게 하실 것이라 보라 그들이 빨리 달려 올 것이로되"
  },
  {
    "verse": 27,
    "zh": "其中沒有疲倦的，絆跌的； 沒有打盹的，睡覺的； 腰帶並不放鬆， 鞋帶也不折斷。",
    "ko": "그 중에 곤핍하여 넘어지는 자도 없을 것이며 조는 자나 자는 자도 없을 것이며 그들의 허리띠는 풀리지 아니하며 그들의 신들메는 끊어지지 아니하며"
  },
  {
    "verse": 28,
    "zh": "他們的箭快利， 弓也上了弦。 馬蹄算如堅石， 車輪好像旋風。",
    "ko": "그들의 살은 날카롭고 모든 활은 당기어졌으며 그 말굽은 부싯돌 같고 차 바퀴는 회리바람 같을 것이며"
  },
  {
    "verse": 29,
    "zh": "他們要吼叫，像母獅子， 咆哮，像少壯獅子； 他們要咆哮抓食， 坦然叼去，無人救回。",
    "ko": "그 부르짖는 것은 암사자 같을 것이요 그 소리지름은 어린 사자들과 같을 것이라 그들이 부르짖으며 물건을 움키어 염려 없이 가져가도 건질 자가 없으리로다"
  },
  {
    "verse": 30,
    "zh": "那日，他們要向以色列人吼叫， 像海浪匉訇； 人若望地，只見黑暗艱難， 光明在雲中變為昏暗。",
    "ko": "그 날에 그들이 바다 물결 소리 같이 백성을 향하여 부르짖으리니 사람이 그 땅을 바라보면 흑암과 고난이 있고 빛은 구름에 가리워져서 어두우리라"
  }
]
