[
  {
    "type": "heading",
    "zh": "十二使徒"
  },
  {
    "verse": 1,
    "zh": "耶穌叫了十二個門徒來，給他們權柄，能趕逐污鬼，並醫治各樣的病症。",
    "ko": "예수께서 그 열두 제자를 부르사 더러운 귀신을 쫓아내며 모든 병과 모든 약한 것을 고치는 권능을 주시니라"
  },
  {
    "verse": 2,
    "zh": "這十二使徒的名：頭一個叫西門（又稱彼得），還有他兄弟安得烈，西庇太的兒子雅各和雅各的兄弟約翰，",
    "ko": "열두 사도의 이름은 이러하니 베드로라 하는 시몬을 비롯하여 그의 형제 안드레와 세베대의 아들 야고보와 그의 형제 요한,"
  },
  {
    "verse": 3,
    "zh": "腓力和巴多羅買，多馬和稅吏馬太，亞勒腓的兒子雅各，和達太，",
    "ko": "빌립과 바돌로매, 도마와 세리 마태, 알패오의 아들 야고보와 다대오,"
  },
  {
    "verse": 4,
    "zh": "奮銳黨的西門，還有賣耶穌的加略人猶大。",
    "ko": "가나안인 시몬과 및 가룟 유다 곧 예수를 판 자라"
  },
  {
    "type": "heading",
    "zh": "十二使徒的使命"
  },
  {
    "verse": 5,
    "zh": "耶穌差這十二個人去，吩咐他們說：「外邦人的路，你們不要走；撒馬利亞人的城，你們不要進；",
    "ko": "예수께서 이 열둘을 내어 보내시며 명하여 가라사대 이방인의 길로도 가지 말고 사마리아인의 고을에도 들어가지 말고"
  },
  {
    "verse": 6,
    "zh": "寧可往以色列家迷失的羊那裏去。",
    "ko": "차라리 이스라엘 집의 잃어버린 양에게로 가라"
  },
  {
    "verse": 7,
    "zh": "隨走隨傳，說『天國近了！』",
    "ko": "가면서 전파하여 말하되 천국이 가까웠다 하고"
  },
  {
    "verse": 8,
    "zh": "醫治病人，叫死人復活，叫長大痲瘋的潔淨，把鬼趕出去。你們白白地得來，也要白白地捨去。",
    "ko": "병든 자를 고치며 죽은 자를 살리며 문둥이를 깨끗하게 하며 귀신을 쫓아내되 너희가 거저 받았으니 거저 주어라"
  },
  {
    "verse": 9,
    "zh": "腰袋裏不要帶金銀銅錢；",
    "ko": "너희 전대에 금이나 은이나 동이나 가지지 말고"
  },
  {
    "verse": 10,
    "zh": "行路不要帶口袋；不要帶兩件褂子，也不要帶鞋和柺杖。因為工人得飲食是應當的。",
    "ko": "여행을 위하여 주머니나 두 벌 옷이나 신이나 지팡이를 가지지 말라 이는 일꾼이 저 먹을 것 받는 것이 마땅함이니라"
  },
  {
    "verse": 11,
    "zh": "你們無論進哪一城，哪一村，要打聽那裏誰是好人，就住在他家，直住到走的時候。",
    "ko": "아무 성이나 촌에 들어가든지 그 중에 합당한 자를 찾아내어 너희 떠나기까지 거기서 머물라"
  },
  {
    "verse": 12,
    "zh": "進他家裏去，要請他的安。",
    "ko": "또 그 집에 들어가면서 평안하기를 빌라"
  },
  {
    "verse": 13,
    "zh": "那家若配得平安，你們所求的平安就必臨到那家；若不配得，你們所求的平安仍歸你們。",
    "ko": "그 집이 이에 합당하면 너희 빈 평안이 거기 임할 것이요 만일 합당치 아니하면 그 평안이 너희에게 돌아올 것이니라"
  },
  {
    "verse": 14,
    "zh": "凡不接待你們、不聽你們話的人，你們離開那家，或是那城的時候，就把腳上的塵土跺下去。",
    "ko": "누구든지 너희를 영접도 아니하고 너희 말을 듣지도 아니하거든 그 집이나 성에서 나가 너희 발의 먼지를 떨어 버리라"
  },
  {
    "verse": 15,
    "zh": "我實在告訴你們，當審判的日子，所多瑪和蛾摩拉所受的，比那城還容易受呢！」",
    "ko": "내가 진실로 너희에게 이르노니 심판날에 소돔과 고모라 땅이 그 성보다 견디기 쉬우리라"
  },
  {
    "type": "heading",
    "zh": "將來的逼迫"
  },
  {
    "verse": 16,
    "zh": "「我差你們去，如同羊進入狼群；所以你們要靈巧像蛇，馴良像鴿子。",
    "ko": "보라 내가 너희를 보냄이 양을 이리 가운데 보냄과 같도다 그러므로 너희는 뱀 같이 지혜롭고 비둘기 같이 순결하라"
  },
  {
    "verse": 17,
    "zh": "你們要防備人；因為他們要把你們交給公會 ，也要在會堂裏鞭打你們，",
    "ko": "사람들을 삼가라 저희가 너희를 공회에 넘겨 주겠고 저희 회당에서 채찍질하리라"
  },
  {
    "verse": 18,
    "zh": "並且你們要為我的緣故被送到諸侯君王面前，對他們和外邦人作見證。",
    "ko": "또 너희가 나를 인하여 총독들과 임금들 앞에 끌려 가리니 이는 저희와 이방인들에게 증거가 되게 하려 하심이라"
  },
  {
    "verse": 19,
    "zh": "你們被交的時候，不要思慮怎樣說話，或說甚麼話。到那時候，必賜給你們當說的話；",
    "ko": "너희를 넘겨 줄 때에 어떻게 또는 무엇을 말할까 염려치 말라 그때에 무슨 말할 것을 주시리니"
  },
  {
    "verse": 20,
    "zh": "因為不是你們自己說的，乃是你們父的靈在你們裏頭說的。",
    "ko": "말하는 이는 너희가 아니라 너희 속에서 말씀하시는 자 곧 너희 아버지의 성령이시니라"
  },
  {
    "verse": 21,
    "zh": "弟兄要把弟兄，父親要把兒子，送到死地；兒女要與父母為敵，害死他們；",
    "ko": "장차 형제가 형제를 아비가 자식을 죽는 데 내어주며 자식들이 부모를 대적하여 죽게 하리라"
  },
  {
    "verse": 22,
    "zh": "並且你們要為我的名被眾人恨惡。惟有忍耐到底的必然得救。",
    "ko": "또 너희가 내 이름을 인하여 모든 사람에게 미움을 받을 것이나 나중까지 견디는 자는 구원을 얻으리라"
  },
  {
    "verse": 23,
    "zh": "有人在這城裏逼迫你們，就逃到那城裏去。我實在告訴你們，以色列的城邑，你們還沒有走遍，人子就到了。",
    "ko": "이 동네에서 너희를 핍박하거든 저 동네로 피하라 내가 진실로 너희에게 이르노니 이스라엘의 모든 동네를 다 다니지 못하여서 인자가 오리라"
  },
  {
    "verse": 24,
    "zh": "學生不能高過先生；僕人不能高過主人。",
    "ko": "제자가 그 선생보다 또는 종이 그 상전보다 높지 못하나니"
  },
  {
    "verse": 25,
    "zh": "學生和先生一樣，僕人和主人一樣，也就罷了。人既罵家主是別西卜，何況他的家人呢？」",
    "ko": "제자가 그 선생 같고 종이 그 상전 같으면 족하도다 집 주인을 바알세불이라 하였거든 하물며 그 집 사람들이랴"
  },
  {
    "type": "heading",
    "zh": "該怕的是誰"
  },
  {
    "verse": 26,
    "zh": "「所以，不要怕他們；因為掩蓋的事沒有不露出來的，隱藏的事沒有不被人知道的。",
    "ko": "그런즉 저희를 두려워하지 말라 감추인 것이 드러나지 않을 것이 없고 숨은 것이 알려지지 않을 것이 없느니라"
  },
  {
    "verse": 27,
    "zh": "我在暗中告訴你們的，你們要在明處說出來；你們耳中所聽的，要在房上宣揚出來。",
    "ko": "내가 너희에게 어두운 데서 이르는 것을 광명한 데서 말하며 너희가 귓속으로 듣는 것을 집 위에서 전파하라"
  },
  {
    "verse": 28,
    "zh": "那殺身體、不能殺靈魂的，不要怕他們；惟有能把身體和靈魂都滅在地獄裏的，正要怕他。",
    "ko": "몸은 죽여도 영혼은 능히 죽이지 못하는 자들을 두려워하지 말고 오직 몸과 영혼을 능히 지옥에 멸하시는 자를 두려워하라"
  },
  {
    "verse": 29,
    "zh": "兩個麻雀不是賣一分銀子嗎？若是你們的父不許，一個也不能掉在地上；",
    "ko": "참새 두 마리가 한 앗사리온에 팔리는 것이 아니냐 그러나 너희 아버지께서 허락지 아니하시면 그 하나라도 땅에 떨어지지 아니하리라"
  },
  {
    "verse": 30,
    "zh": "就是你們的頭髮也都被數過了。",
    "ko": "너희에게는 머리털까지 다 세신바 되었나니"
  },
  {
    "verse": 31,
    "zh": "所以，不要懼怕，你們比許多麻雀還貴重！」",
    "ko": "두려워하지 말라 너희는 많은 참새보다 귀하니라"
  },
  {
    "type": "heading",
    "zh": "在人的面前承認基督"
  },
  {
    "verse": 32,
    "zh": "「凡在人面前認我的，我在我天上的父面前也必認他；",
    "ko": "누구든지 사람 앞에서 나를 시인하면 나도 하늘에 계신 내 아버지 앞에서 저를 시인할 것이요"
  },
  {
    "verse": 33,
    "zh": "凡在人面前不認我的，我在我天上的父面前也必不認他。」",
    "ko": "누구든지 사람 앞에서 나를 부인하면 나도 하늘에 계신 내 아버지 앞에서 저를 부인하리라"
  },
  {
    "type": "heading",
    "zh": "不是和平，而是刀劍"
  },
  {
    "verse": 34,
    "zh": "「你們不要想我來是叫地上太平；我來並不是叫地上太平，乃是叫地上動刀兵。",
    "ko": "내가 세상에 화평을 주러 온 줄로 생각지 말라 화평이 아니요 검을 주러 왔노라"
  },
  {
    "verse": 35,
    "zh": "因為我來是叫 人與父親生疏， 女兒與母親生疏， 媳婦與婆婆生疏。",
    "ko": "내가 온 것은 사람이 그 아비와, 딸이 어미와, 며느리가 시어미와 불화하게 하려 함이니"
  },
  {
    "verse": 36,
    "zh": "人的仇敵就是自己家裏的人。",
    "ko": "사람의 원수가 자기 집안 식구리라"
  },
  {
    "verse": 37,
    "zh": "「愛父母過於愛我的，不配作我的門徒；愛兒女過於愛我的，不配作我的門徒；",
    "ko": "아비나 어미를 나보다 더 사랑하는 자는 내게 합당치 아니하고 아들이나 딸을 나보다 더 사랑하는 자도 내게 합당치 아니하고"
  },
  {
    "verse": 38,
    "zh": "不背著他的十字架跟從我的，也不配作我的門徒。",
    "ko": "또 자기 십자가를 지고 나를 좇지 않는 자도 내게 합당치 아니하니라"
  },
  {
    "verse": 39,
    "zh": "得著生命的，將要失喪生命；為我失喪生命的，將要得著生命。」",
    "ko": "자기 목숨을 얻는 자는 잃을 것이요 나를 위하여 자기 목숨을 잃는 자는 얻으리라"
  },
  {
    "type": "heading",
    "zh": "論報賞"
  },
  {
    "verse": 40,
    "zh": "「人接待你們就是接待我；接待我就是接待那差我來的。",
    "ko": "너희를 영접하는 자는 나를 영접하는 것이요 나를 영접하는 자는 나 보내신 이를 영접하는 것이니라"
  },
  {
    "verse": 41,
    "zh": "人因為先知的名接待先知，必得先知所得的賞賜；人因為義人的名接待義人，必得義人所得的賞賜。",
    "ko": "선지자의 이름으로 선지자를 영접하는 자는 선지자의 상을 받을 것이요 의인의 이름으로 의인을 영접하는 자는 의인의 상을 받을 것이요"
  },
  {
    "verse": 42,
    "zh": "無論何人，因為門徒的名，只把一杯涼水給這小子裏的一個喝，我實在告訴你們，這人不能不得賞賜。」",
    "ko": "또 누구든지 제자의 이름으로 이 소자 중 하나에게 냉수 한 그릇이라도 주는 자는 내가 진실로 너희에게 이르노니 그 사람이 결단코 상을 잃지 아니하리라 하시니라"
  }
]
