[
  {
    "type": "heading",
    "zh": "舉哀時的禁例"
  },
  {
    "verse": 1,
    "zh": "「你們是耶和華－你們神的兒女。不可為死人用刀劃身，也不可將額上剃光；",
    "ko": "너희는 너희 하나님 여호와의 자녀니 죽은 자를 위하여 자기 몸을 베지 말며 눈썹 사이 이마 위의 털을 밀지 말라"
  },
  {
    "verse": 2,
    "zh": "因為你歸耶和華－你神為聖潔的民，耶和華從地上的萬民中揀選你特作自己的子民。」",
    "ko": "너는 너의 하나님 여호와의 성민이라 여호와께서 지상 만민 중에서 너를 택하여 자기의 기업의 백성을 삼으셨느니라"
  },
  {
    "type": "heading",
    "zh": "潔淨和不潔淨的動物"
  },
  {
    "verse": 3,
    "zh": "「凡可憎的物都不可吃。",
    "ko": "너는 가증한 물건은 무엇이든지 먹지 말라"
  },
  {
    "verse": 4,
    "zh": "可吃的牲畜就是牛、綿羊、山羊、",
    "ko": "너희의 먹을 만한 짐승은 이러하니 곧 소와 양과 염소와"
  },
  {
    "verse": 5,
    "zh": "鹿、羚羊、麅子、野山羊、麋鹿、黃羊、青羊。",
    "ko": "사슴과 노루와 불그스럼한 사슴과 산염소와 볼기 흰 노루와 뿔 긴 사슴과 산양들"
  },
  {
    "verse": 6,
    "zh": "凡分蹄成為兩瓣又倒嚼的走獸，你們都可以吃。",
    "ko": "무릇 짐승 중에 굽이 갈라져 쪽발도 되고 새김질도 하는 것은 너희가 먹을 것이니라"
  },
  {
    "verse": 7,
    "zh": "但那些倒嚼或是分蹄之中不可吃的乃是駱駝、兔子、沙番－因為是倒嚼不分蹄，就與你們不潔淨；",
    "ko": "다만 새김질을 하거나 굽이 갈라진 짐승 중에도 너희가 먹지 못할 것은 이것이니 곧 약대와 토끼와 사반 그것들은 새김질을 하나 굽이 갈라지지 아니하였으니 너희에게 부정하고"
  },
  {
    "verse": 8,
    "zh": "豬－因為是分蹄卻不倒嚼，就與你們不潔淨。這些獸的肉，你們不可吃，死的也不可摸。",
    "ko": "돼지는 굽은 갈라졌으나 새김질을 못하므로 너희에게 부정하니 너희는 이런 것의 고기를 먹지 말 것이며 그 사체도 만지지 말 것이니라"
  },
  {
    "verse": 9,
    "zh": "「水中可吃的乃是這些：凡有翅有鱗的都可以吃；",
    "ko": "물에 있는 어족 중에 이런 것은 너희가 먹을 것이니 무릇 지느러미와 비늘 있는 것은 너희가 먹을 것이요"
  },
  {
    "verse": 10,
    "zh": "凡無翅無鱗的都不可吃，是與你們不潔淨。",
    "ko": "무릇 지느러미와 비늘이 없는 것은 너희가 먹지 말지니 이는 너희에게 부정하니라"
  },
  {
    "verse": 11,
    "zh": "「凡潔淨的鳥，你們都可以吃。",
    "ko": "무릇 정한 새는 너희가 먹으려니와"
  },
  {
    "verse": 12,
    "zh": "不可吃的乃是鵰、狗頭鵰、紅頭鵰、",
    "ko": "이런 것은 너희가 먹지 못할지니 곧 독수리와 솔개와 어응과"
  },
  {
    "verse": 13,
    "zh": "鸇、小鷹、鷂鷹與其類，",
    "ko": "매와 새매와 매의 종류와"
  },
  {
    "verse": 14,
    "zh": "烏鴉與其類，",
    "ko": "까마귀 종류와"
  },
  {
    "verse": 15,
    "zh": "鴕鳥、夜鷹、魚鷹、鷹與其類，",
    "ko": "타조와 다호마스와 갈매기와 새매 종류와"
  },
  {
    "verse": 16,
    "zh": "鴞鳥、貓頭鷹、角鴟、",
    "ko": "올빼미와 부엉이와 따오기와"
  },
  {
    "verse": 17,
    "zh": "鵜鶘、禿鵰、鸕鶿、",
    "ko": "당아와 올응과 노자와"
  },
  {
    "verse": 18,
    "zh": "鸛、鷺鷥與其類，戴鵀與蝙蝠。",
    "ko": "학과 황새 종류와 대승과 박쥐며"
  },
  {
    "verse": 19,
    "zh": "凡有翅膀爬行的物是與你們不潔淨，都不可吃。",
    "ko": "또 무릇 날기도 하고 기어 다니기도 하는 것은 너희에게 부정하니 너희는 먹지 말 것이나"
  },
  {
    "verse": 20,
    "zh": "凡潔淨的鳥，你們都可以吃。",
    "ko": "무릇 정한 새는 너희가 먹을지니라"
  },
  {
    "verse": 21,
    "zh": "「凡自死的，你們都不可吃，可以給你城裏寄居的吃，或賣與外人吃，因為你是歸耶和華－你神為聖潔的民。",
    "ko": "너희는 너희 하나님 여호와의 성민이라 무릇 스스로 죽은 것은 먹지 말 것이니 그것을 성중에 우거하는 객에게 주어 먹게 하거나 이방인에게 팔아도 가하니라 너는 염소 새끼를 그 어미의 젖에 삶지 말지니라"
  },
  {
    "type": "heading",
    "zh": "十分獻一的條例"
  },
  {
    "verse": 22,
    "zh": "「你要把你撒種所產的，就是你田地每年所出的，十分取一分；",
    "ko": "너는 마땅히 매년에 토지 소산의 십일조를 드릴 것이며"
  },
  {
    "verse": 23,
    "zh": "又要把你的五穀、新酒、和油的十分之一，並牛群羊群中頭生的，吃在耶和華－你神面前，就是他所選擇要立為他名的居所。這樣，你可以學習時常敬畏耶和華－你的神。",
    "ko": "네 하나님 여호와 앞 곧 여호와께서 그 이름을 두시려고 택하신 곳에서 네 곡식과 포도주와 기름의 십일조를 먹으며 또 네 우양의 처음 난 것을 먹고 네 하나님 여호와 경외하기를 항상 배울 것이니라"
  },
  {
    "verse": 24,
    "zh": "當耶和華－你神賜福與你的時候，耶和華－你神所選擇要立為他名的地方若離你太遠，那路也太長，使你不能把這物帶到那裏去，",
    "ko": "그러나 네 하나님 여호와께서 그 이름을 두시려고 택하신 곳이 네게서 너무 멀고 행로가 어려워서 그 풍부히 주신 것을 가지고 갈 수 없거든"
  },
  {
    "verse": 25,
    "zh": "你就可以換成銀子，將銀子包起來，拿在手中，往耶和華－你神所要選擇的地方去。",
    "ko": "그것을 돈으로 바꾸어 그 돈을 싸서 가지고 네 하나님 여호와의 택하신 곳으로 가서"
  },
  {
    "verse": 26,
    "zh": "你用這銀子，隨心所欲，或買牛羊，或買清酒濃酒，凡你心所想的都可以買；你和你的家屬在耶和華－你神的面前吃喝快樂。",
    "ko": "무릇 네 마음에 좋아하는 것을 그 돈으로 사되 우양이나 포도주나 독주 등 무릇 네 마음에 원하는 것을 구하고 거기 네 하나님 여호와의 앞에서 너와 네 권속이 함께 먹고 즐거워할 것이며"
  },
  {
    "verse": 27,
    "zh": "「住在你城裏的利未人，你不可丟棄他，因為他在你們中間無分無業。",
    "ko": "네 성읍에 거하는 레위인은 너희 중에 분깃이나 기업이 없는 자니 또한 저버리지 말지니라"
  },
  {
    "verse": 28,
    "zh": "每逢三年的末一年，你要將本年的土產十分之一都取出來，積存在你的城中。",
    "ko": "매 삼년 끝에 그 해 소산의 십분 일을 다 내어 네 성읍에 저축하여"
  },
  {
    "verse": 29,
    "zh": "在你城裏無分無業的利未人，和你城裏寄居的，並孤兒寡婦，都可以來，吃得飽足。這樣，耶和華－你的神必在你手裏所辦的一切事上賜福與你。」",
    "ko": "너희 중에 분깃이나 기업이 없는 레위인과 네 성중에 우거하는 객과 및 고아와 과부들로 와서 먹어 배부르게 하라 그리하면 네 하나님 여호와께서 너의 손으로 하는 범사에 네게 축복을 주시리라"
  }
]
